datoso/__init__.py
datoso/__main__.py
datoso/datoso.ini
datoso/mia.json
datoso/seeds.txt
datoso/systems.json
datoso/actions/__init__.py
datoso/actions/processor.py
datoso/commands/__init__.py
datoso/commands/argparser.py
datoso/commands/commands.py
datoso/commands/doctor.py
datoso/commands/seed.py
datoso/commands/helpers/__init__.py
datoso/commands/helpers/dat.py
datoso/commands/helpers/seed.py
datoso/configuration/__init__.py
datoso/configuration/configuration.py
datoso/configuration/folder_helper.py
datoso/configuration/logger.py
datoso/database/__init__.py
datoso/database/models/__init__.py
datoso/database/models/dat.py
datoso/database/seeds/__init__.py
datoso/database/seeds/dat_repos.py
datoso/database/seeds/dat_rules.py
datoso/database/seeds/mia.py
datoso/helpers/__init__.py
datoso/helpers/download.py
datoso/helpers/executor.py
datoso/helpers/file_utils.py
datoso/helpers/plugins.py
datoso/helpers/request_utils.py
datoso/mias/__init__.py
datoso/mias/mia.py
datoso/repositories/__init__.py
datoso/repositories/dat_file.py
datoso/repositories/dedupe.py
datoso/repositories/hashes_index.py
datoso/seeds/__init__.py
datoso/seeds/rules.py
datoso/seeds/unknown_seed.py
datoso-1.1.1.dist-info/LICENSE
datoso-1.1.1.dist-info/METADATA
datoso-1.1.1.dist-info/WHEEL
datoso-1.1.1.dist-info/entry_points.txt
datoso-1.1.1.dist-info/top_level.txt
datoso-1.1.1.dist-info/RECORD
