Metadata-Version: 2.1
Name: datoso
Version: 1.1.1
Summary: Python command line tool to download and organize your Rom Dat files.
Author-email: Lacides Miranda <laromicas@hotmail.com>
License: MIT License
Project-URL: Source Code, https://github.com/laromicas/datoso
Keywords: emulators,roms
Classifier: Development Status :: 5 - Production/Stable
Classifier: Environment :: Console
Classifier: License :: OSI Approved :: MIT License
Classifier: Operating System :: POSIX :: Linux
Classifier: Programming Language :: Python :: 3
Classifier: Topic :: System :: Emulators
Classifier: Topic :: System :: Archiving
Requires-Python: >=3.11
License-File: LICENSE
Requires-Dist: dataclasses-json (>=0.6.4)
Requires-Dist: pydantic (==1.10.9)
Requires-Dist: python-dateutil (>=2.8.2)
Requires-Dist: requests (>=2.31.0)
Requires-Dist: rich (>=14.0.0)
Requires-Dist: tabulate (>=0.9.0)
Requires-Dist: tinydb (>=4.7.1)
Requires-Dist: xmltodict (>=0.13.0)
Provides-Extra: all
Requires-Dist: datoso-seed-fbneo (>=1.0.2) ; extra == 'all'
Requires-Dist: datoso-seed-enhanced (>=1.1.0) ; extra == 'all'
Requires-Dist: datoso-seed-nointro (>=1.1.1) ; extra == 'all'
Requires-Dist: datoso-seed-pleasuredome (>=1.1.1) ; extra == 'all'
Requires-Dist: datoso-seed-redump (>=1.0.1) ; extra == 'all'
Requires-Dist: datoso-seed-tdc (>=1.1.0) ; extra == 'all'
Requires-Dist: datoso-seed-translatedenglish (>=1.1.1) ; extra == 'all'
Requires-Dist: datoso-seed-vpinmame (>=1.0.2) ; extra == 'all'
Provides-Extra: dev
Requires-Dist: ruff (>=0.6.3) ; extra == 'dev'
Requires-Dist: line-profiler (==4.1.3) ; extra == 'dev'
Requires-Dist: sphinx (>=8.0.0) ; extra == 'dev'
Requires-Dist: sphinx-rtd-theme (>=3.0.0) ; extra == 'dev'
Requires-Dist: setuptools ; extra == 'dev'
Provides-Extra: enhanced
Requires-Dist: datoso-seed-enhanced (>=1.1.0) ; extra == 'enhanced'
Provides-Extra: fbneo
Requires-Dist: datoso-seed-fbneo (>=1.0.2) ; extra == 'fbneo'
Provides-Extra: nointro
Requires-Dist: datoso-seed-nointro (>=1.1.1) ; extra == 'nointro'
Provides-Extra: pleasuredome
Requires-Dist: datoso-seed-pleasuredome (>=1.1.1) ; extra == 'pleasuredome'
Provides-Extra: redump
Requires-Dist: datoso-seed-redump (>=1.0.1) ; extra == 'redump'
Provides-Extra: tdc
Requires-Dist: datoso-seed-tdc (>=1.1.0) ; extra == 'tdc'
Provides-Extra: test
Requires-Dist: pytest (>=8.0.0) ; extra == 'test'
Requires-Dist: pytest-cov (>=6.0.0) ; extra == 'test'
Requires-Dist: pytest-mock (>=3.14.0) ; extra == 'test'
Requires-Dist: pytest-xdist (>=3.6.0) ; extra == 'test'
Provides-Extra: translatedenglish
Requires-Dist: datoso-seed-translatedenglish (>=1.1.1) ; extra == 'translatedenglish'
Provides-Extra: vpinmame
Requires-Dist: datoso-seed-vpinmame (>=1.0.2) ; extra == 'vpinmame'
